[
  {
    "serial_number": 1,
    "word": "તરીકે"
  },
  {
    "serial_number": 2,
    "word": "હું"
  },
  {
    "serial_number": 3,
    "word": "તેના"
  },
  {
    "serial_number": 4,
    "word": "કે"
  },
  {
    "serial_number": 5,
    "word": "તે"
  },
  {
    "serial_number": 6,
    "word": "હતી"
  },
  {
    "serial_number": 7,
    "word": "માટે"
  },
  {
    "serial_number": 8,
    "word": "પર"
  },
  {
    "serial_number": 9,
    "word": "છે"
  },
  {
    "serial_number": 10,
    "word": "સાથે"
  },
  {
    "serial_number": 11,
    "word": "તેઓ"
  },
  {
    "serial_number": 12,
    "word": "પ્રયત્ન"
  },
  {
    "serial_number": 13,
    "word": "પર"
  },
  {
    "serial_number": 14,
    "word": "એક"
  },
  {
    "serial_number": 15,
    "word": "છે"
  },
  {
    "serial_number": 16,
    "word": "આ"
  },
  {
    "serial_number": 17,
    "word": "થી"
  },
  {
    "serial_number": 18,
    "word": "દ્વારા"
  },
  {
    "serial_number": 19,
    "word": "ગરમ"
  },
  {
    "serial_number": 20,
    "word": "શબ્દ"
  },
  {
    "serial_number": 21,
    "word": "પરંતુ"
  },
  {
    "serial_number": 22,
    "word": "શું"
  },
  {
    "serial_number": 23,
    "word": "કેટલાક"
  },
  {
    "serial_number": 24,
    "word": "છે"
  },
  {
    "serial_number": 25,
    "word": "તે"
  },
  {
    "serial_number": 26,
    "word": "તમે"
  },
  {
    "serial_number": 27,
    "word": "અથવા"
  },
  {
    "serial_number": 28,
    "word": "હતી"
  },
  {
    "serial_number": 29,
    "word": "આ"
  },
  {
    "serial_number": 30,
    "word": "ના"
  },
  {
    "serial_number": 31,
    "word": "માટે"
  },
  {
    "serial_number": 32,
    "word": "અને"
  },
  {
    "serial_number": 33,
    "word": "એક"
  },
  {
    "serial_number": 34,
    "word": "માં"
  },
  {
    "serial_number": 35,
    "word": "અમે"
  },
  {
    "serial_number": 36,
    "word": "આ કરી શકો છો"
  },
  {
    "serial_number": 37,
    "word": "બહાર"
  },
  {
    "serial_number": 38,
    "word": "અન્ય"
  },
  {
    "serial_number": 39,
    "word": "હતા"
  },
  {
    "serial_number": 40,
    "word": "જે"
  },
  {
    "serial_number": 41,
    "word": "કરી"
  },
  {
    "serial_number": 42,
    "word": "તેમના"
  },
  {
    "serial_number": 43,
    "word": "સમય"
  },
  {
    "serial_number": 44,
    "word": "જો"
  },
  {
    "serial_number": 45,
    "word": "કરશે"
  },
  {
    "serial_number": 46,
    "word": "કેવી રીતે"
  },
  {
    "serial_number": 47,
    "word": "જણાવ્યું હતું કે,"
  },
  {
    "serial_number": 48,
    "word": "એક"
  },
  {
    "serial_number": 49,
    "word": "દરેક"
  },
  {
    "serial_number": 50,
    "word": "કહી"
  },
  {
    "serial_number": 51,
    "word": "કરે"
  },
  {
    "serial_number": 52,
    "word": "સમૂહ"
  },
  {
    "serial_number": 53,
    "word": "ત્રણ"
  },
  {
    "serial_number": 54,
    "word": "માંગો છો"
  },
  {
    "serial_number": 55,
    "word": "હવા"
  },
  {
    "serial_number": 56,
    "word": "સાથે સાથે"
  },
  {
    "serial_number": 57,
    "word": "પણ"
  },
  {
    "serial_number": 58,
    "word": "રમવા"
  },
  {
    "serial_number": 59,
    "word": "નાના"
  },
  {
    "serial_number": 60,
    "word": "અંત"
  },
  {
    "serial_number": 61,
    "word": "મૂકી"
  },
  {
    "serial_number": 62,
    "word": "ઘર"
  },
  {
    "serial_number": 63,
    "word": "વાંચો"
  },
  {
    "serial_number": 64,
    "word": "હાથ"
  },
  {
    "serial_number": 65,
    "word": "પોર્ટ"
  },
  {
    "serial_number": 66,
    "word": "મોટા"
  },
  {
    "serial_number": 67,
    "word": "જોડણી"
  },
  {
    "serial_number": 68,
    "word": "ઉમેરો"
  },
  {
    "serial_number": 69,
    "word": "પણ"
  },
  {
    "serial_number": 70,
    "word": "જમીન"
  },
  {
    "serial_number": 71,
    "word": "અહીં"
  },
  {
    "serial_number": 72,
    "word": "જ જોઈએ"
  },
  {
    "serial_number": 73,
    "word": "મોટા"
  },
  {
    "serial_number": 74,
    "word": "ઉચ્ચ"
  },
  {
    "serial_number": 75,
    "word": "જેમ કે"
  },
  {
    "serial_number": 76,
    "word": "અનુસરો"
  },
  {
    "serial_number": 77,
    "word": "અધિનિયમ"
  },
  {
    "serial_number": 78,
    "word": "શા માટે"
  },
  {
    "serial_number": 79,
    "word": "પૂછો"
  },
  {
    "serial_number": 80,
    "word": "પુરુષો"
  },
  {
    "serial_number": 81,
    "word": "ફેરફાર"
  },
  {
    "serial_number": 82,
    "word": "ગયા"
  },
  {
    "serial_number": 83,
    "word": "પ્રકાશ"
  },
  {
    "serial_number": 84,
    "word": "પ્રકારની"
  },
  {
    "serial_number": 85,
    "word": "બંધ"
  },
  {
    "serial_number": 86,
    "word": "જરૂર"
  },
  {
    "serial_number": 87,
    "word": "ઘર"
  },
  {
    "serial_number": 88,
    "word": "ચિત્ર"
  },
  {
    "serial_number": 89,
    "word": "પ્રયાસ"
  },
  {
    "serial_number": 90,
    "word": "અમને"
  },
  {
    "serial_number": 91,
    "word": "ફરીથી"
  },
  {
    "serial_number": 92,
    "word": "પ્રાણી"
  },
  {
    "serial_number": 93,
    "word": "બિંદુ"
  },
  {
    "serial_number": 94,
    "word": "માતા"
  },
  {
    "serial_number": 95,
    "word": "વિશ્વ"
  },
  {
    "serial_number": 96,
    "word": "નજીક"
  },
  {
    "serial_number": 97,
    "word": "બિલ્ડ"
  },
  {
    "serial_number": 98,
    "word": "સ્વ"
  },
  {
    "serial_number": 99,
    "word": "પૃથ્વી"
  },
  {
    "serial_number": 100,
    "word": "પિતા"
  },
  {
    "serial_number": 101,
    "word": "કોઈપણ"
  },
  {
    "serial_number": 102,
    "word": "નવા"
  },
  {
    "serial_number": 103,
    "word": "કામ"
  },
  {
    "serial_number": 104,
    "word": "ભાગ"
  },
  {
    "serial_number": 105,
    "word": "લો"
  },
  {
    "serial_number": 106,
    "word": "વિચાર"
  },
  {
    "serial_number": 107,
    "word": "સ્થળ"
  },
  {
    "serial_number": 108,
    "word": "કરી"
  },
  {
    "serial_number": 109,
    "word": "રહે છે"
  },
  {
    "serial_number": 110,
    "word": "જ્યાં"
  },
  {
    "serial_number": 111,
    "word": "પછી"
  },
  {
    "serial_number": 112,
    "word": "પાછા"
  },
  {
    "serial_number": 113,
    "word": "ઓછી"
  },
  {
    "serial_number": 114,
    "word": "માત્ર"
  },
  {
    "serial_number": 115,
    "word": "રાઉન્ડ"
  },
  {
    "serial_number": 116,
    "word": "માણસ"
  },
  {
    "serial_number": 117,
    "word": "વર્ષ"
  },
  {
    "serial_number": 118,
    "word": "આવી"
  },
  {
    "serial_number": 119,
    "word": "શો"
  },
  {
    "serial_number": 120,
    "word": "દરેક"
  },
  {
    "serial_number": 121,
    "word": "સારું"
  },
  {
    "serial_number": 122,
    "word": "મને"
  },
  {
    "serial_number": 123,
    "word": "આપે"
  },
  {
    "serial_number": 124,
    "word": "અમારા"
  },
  {
    "serial_number": 125,
    "word": "હેઠળ"
  },
  {
    "serial_number": 126,
    "word": "નામ"
  },
  {
    "serial_number": 127,
    "word": "ખૂબ"
  },
  {
    "serial_number": 128,
    "word": "દ્વારા"
  },
  {
    "serial_number": 129,
    "word": "માત્ર"
  },
  {
    "serial_number": 130,
    "word": "ફોર્મ"
  },
  {
    "serial_number": 131,
    "word": "સજા"
  },
  {
    "serial_number": 132,
    "word": "મહાન"
  },
  {
    "serial_number": 133,
    "word": "લાગે છે"
  },
  {
    "serial_number": 134,
    "word": "કહે"
  },
  {
    "serial_number": 135,
    "word": "મદદ"
  },
  {
    "serial_number": 136,
    "word": "ઓછી"
  },
  {
    "serial_number": 137,
    "word": "રેખા"
  },
  {
    "serial_number": 138,
    "word": "અલગ"
  },
  {
    "serial_number": 139,
    "word": "વળાંક"
  },
  {
    "serial_number": 140,
    "word": "કારણ"
  },
  {
    "serial_number": 141,
    "word": "ખૂબ"
  },
  {
    "serial_number": 142,
    "word": "અર્થ"
  },
  {
    "serial_number": 143,
    "word": "પહેલાં"
  },
  {
    "serial_number": 144,
    "word": "ચાલ"
  },
  {
    "serial_number": 145,
    "word": "અધિકાર"
  },
  {
    "serial_number": 146,
    "word": "છોકરો"
  },
  {
    "serial_number": 147,
    "word": "જૂના"
  },
  {
    "serial_number": 148,
    "word": "પણ"
  },
  {
    "serial_number": 149,
    "word": "જ"
  },
  {
    "serial_number": 150,
    "word": "તે"
  },
  {
    "serial_number": 151,
    "word": "બધા"
  },
  {
    "serial_number": 152,
    "word": "ત્યાં"
  },
  {
    "serial_number": 153,
    "word": "જ્યારે"
  },
  {
    "serial_number": 154,
    "word": "અપ"
  },
  {
    "serial_number": 155,
    "word": "ઉપયોગ"
  },
  {
    "serial_number": 156,
    "word": "તમારા"
  },
  {
    "serial_number": 157,
    "word": "માર્ગ"
  },
  {
    "serial_number": 158,
    "word": "વિશે"
  },
  {
    "serial_number": 159,
    "word": "ઘણા"
  },
  {
    "serial_number": 160,
    "word": "પછી"
  },
  {
    "serial_number": 161,
    "word": "તેમને"
  },
  {
    "serial_number": 162,
    "word": "લખવા"
  },
  {
    "serial_number": 163,
    "word": "કરશે"
  },
  {
    "serial_number": 164,
    "word": "જેમ"
  },
  {
    "serial_number": 165,
    "word": "તેથી"
  },
  {
    "serial_number": 166,
    "word": "આ"
  },
  {
    "serial_number": 167,
    "word": "તેના"
  },
  {
    "serial_number": 168,
    "word": "લાંબા"
  },
  {
    "serial_number": 169,
    "word": "કરો"
  },
  {
    "serial_number": 170,
    "word": "વસ્તુ"
  },
  {
    "serial_number": 171,
    "word": "જુઓ"
  },
  {
    "serial_number": 172,
    "word": "તેને"
  },
  {
    "serial_number": 173,
    "word": "બે"
  },
  {
    "serial_number": 174,
    "word": "છે"
  },
  {
    "serial_number": 175,
    "word": "જુઓ"
  },
  {
    "serial_number": 176,
    "word": "વધુ"
  },
  {
    "serial_number": 177,
    "word": "દિવસ"
  },
  {
    "serial_number": 178,
    "word": "કરી શકે છે"
  },
  {
    "serial_number": 179,
    "word": "જાઓ"
  },
  {
    "serial_number": 180,
    "word": "આવે"
  },
  {
    "serial_number": 181,
    "word": "હતી"
  },
  {
    "serial_number": 182,
    "word": "નંબર"
  },
  {
    "serial_number": 183,
    "word": "ધ્વનિ"
  },
  {
    "serial_number": 184,
    "word": "કોઈ"
  },
  {
    "serial_number": 185,
    "word": "સૌથી"
  },
  {
    "serial_number": 186,
    "word": "લોકો"
  },
  {
    "serial_number": 187,
    "word": "મારા"
  },
  {
    "serial_number": 188,
    "word": "પર"
  },
  {
    "serial_number": 189,
    "word": "ખબર"
  },
  {
    "serial_number": 190,
    "word": "પાણી"
  },
  {
    "serial_number": 191,
    "word": "કરતાં"
  },
  {
    "serial_number": 192,
    "word": "કૉલ"
  },
  {
    "serial_number": 193,
    "word": "પ્રથમ"
  },
  {
    "serial_number": 194,
    "word": "જે"
  },
  {
    "serial_number": 195,
    "word": "કરી શકે છે"
  },
  {
    "serial_number": 196,
    "word": "નીચે"
  },
  {
    "serial_number": 197,
    "word": "બાજુ"
  },
  {
    "serial_number": 198,
    "word": "આવી"
  },
  {
    "serial_number": 199,
    "word": "હવે"
  },
  {
    "serial_number": 200,
    "word": "શોધવા"
  },
  {
    "serial_number": 201,
    "word": "વડા"
  },
  {
    "serial_number": 202,
    "word": "ઊભા"
  },
  {
    "serial_number": 203,
    "word": "પોતાના"
  },
  {
    "serial_number": 204,
    "word": "પાનું"
  },
  {
    "serial_number": 205,
    "word": "જોઈએ"
  },
  {
    "serial_number": 206,
    "word": "દેશ"
  },
  {
    "serial_number": 207,
    "word": "મળી"
  },
  {
    "serial_number": 208,
    "word": "જવાબ"
  },
  {
    "serial_number": 209,
    "word": "શાળા"
  },
  {
    "serial_number": 210,
    "word": "વૃદ્ધિ"
  },
  {
    "serial_number": 211,
    "word": "અભ્યાસ"
  },
  {
    "serial_number": 212,
    "word": "હજુ પણ"
  },
  {
    "serial_number": 213,
    "word": "જાણવા"
  },
  {
    "serial_number": 214,
    "word": "પ્લાન્ટ"
  },
  {
    "serial_number": 215,
    "word": "કવર"
  },
  {
    "serial_number": 216,
    "word": "ખોરાક"
  },
  {
    "serial_number": 217,
    "word": "સૂર્ય"
  },
  {
    "serial_number": 218,
    "word": "ચાર"
  },
  {
    "serial_number": 219,
    "word": "વચ્ચે"
  },
  {
    "serial_number": 220,
    "word": "રાજ્ય"
  },
  {
    "serial_number": 221,
    "word": "રાખો"
  },
  {
    "serial_number": 222,
    "word": "આંખ"
  },
  {
    "serial_number": 223,
    "word": "ક્યારેય"
  },
  {
    "serial_number": 224,
    "word": "છેલ્લા"
  },
  {
    "serial_number": 225,
    "word": "દો"
  },
  {
    "serial_number": 226,
    "word": "વિચાર્યું"
  },
  {
    "serial_number": 227,
    "word": "શહેર"
  },
  {
    "serial_number": 228,
    "word": "વૃક્ષ"
  },
  {
    "serial_number": 229,
    "word": "પાર"
  },
  {
    "serial_number": 230,
    "word": "ફાર્મ"
  },
  {
    "serial_number": 231,
    "word": "હાર્ડ"
  },
  {
    "serial_number": 232,
    "word": "શરૂઆત"
  },
  {
    "serial_number": 233,
    "word": "કદાચ"
  },
  {
    "serial_number": 234,
    "word": "વાર્તા"
  },
  {
    "serial_number": 235,
    "word": "લાકડાં"
  },
  {
    "serial_number": 236,
    "word": "અત્યાર સુધી"
  },
  {
    "serial_number": 237,
    "word": "સમુદ્ર"
  },
  {
    "serial_number": 238,
    "word": "ડ્રો"
  },
  {
    "serial_number": 239,
    "word": "બાકી"
  },
  {
    "serial_number": 240,
    "word": "અંતમાં"
  },
  {
    "serial_number": 241,
    "word": "રન"
  },
  {
    "serial_number": 242,
    "word": "ન"
  },
  {
    "serial_number": 243,
    "word": "જ્યારે"
  },
  {
    "serial_number": 244,
    "word": "પ્રેસ"
  },
  {
    "serial_number": 245,
    "word": "બંધ"
  },
  {
    "serial_number": 246,
    "word": "રાત"
  },
  {
    "serial_number": 247,
    "word": "વાસ્તવિક"
  },
  {
    "serial_number": 248,
    "word": "જીવન"
  },
  {
    "serial_number": 249,
    "word": "થોડા"
  },
  {
    "serial_number": 250,
    "word": "ઉત્તર"
  },
  {
    "serial_number": 251,
    "word": "પુસ્તક"
  },
  {
    "serial_number": 252,
    "word": "ચાલુ"
  },
  {
    "serial_number": 253,
    "word": "લીધો"
  },
  {
    "serial_number": 254,
    "word": "વિજ્ઞાન"
  },
  {
    "serial_number": 255,
    "word": "ખાય"
  },
  {
    "serial_number": 256,
    "word": "રૂમ"
  },
  {
    "serial_number": 257,
    "word": "મિત્ર"
  },
  {
    "serial_number": 258,
    "word": "શરૂ કર્યું"
  },
  {
    "serial_number": 259,
    "word": "વિચાર"
  },
  {
    "serial_number": 260,
    "word": "માછલી"
  },
  {
    "serial_number": 261,
    "word": "પર્વત"
  },
  {
    "serial_number": 262,
    "word": "બંધ"
  },
  {
    "serial_number": 263,
    "word": "એક વખત"
  },
  {
    "serial_number": 264,
    "word": "આધાર"
  },
  {
    "serial_number": 265,
    "word": "સાંભળવા"
  },
  {
    "serial_number": 266,
    "word": "ઘોડો"
  },
  {
    "serial_number": 267,
    "word": "કટ"
  },
  {
    "serial_number": 268,
    "word": "ખાતરી કરો"
  },
  {
    "serial_number": 269,
    "word": "જુઓ"
  },
  {
    "serial_number": 270,
    "word": "રંગ"
  },
  {
    "serial_number": 271,
    "word": "ચહેરો"
  },
  {
    "serial_number": 272,
    "word": "લાકડું"
  },
  {
    "serial_number": 273,
    "word": "મુખ્ય"
  },
  {
    "serial_number": 274,
    "word": "ઓપન"
  },
  {
    "serial_number": 275,
    "word": "લાગે"
  },
  {
    "serial_number": 276,
    "word": "એક સાથે"
  },
  {
    "serial_number": 277,
    "word": "આગામી"
  },
  {
    "serial_number": 278,
    "word": "સફેદ"
  },
  {
    "serial_number": 279,
    "word": "બાળકો"
  },
  {
    "serial_number": 280,
    "word": "શરૂ"
  },
  {
    "serial_number": 281,
    "word": "મળી"
  },
  {
    "serial_number": 282,
    "word": "ચાલવા"
  },
  {
    "serial_number": 283,
    "word": "ઉદાહરણ"
  },
  {
    "serial_number": 284,
    "word": "સરળ"
  },
  {
    "serial_number": 285,
    "word": "કાગળ"
  },
  {
    "serial_number": 286,
    "word": "જૂથ"
  },
  {
    "serial_number": 287,
    "word": "હંમેશા"
  },
  {
    "serial_number": 288,
    "word": "સંગીત"
  },
  {
    "serial_number": 289,
    "word": "તે"
  },
  {
    "serial_number": 290,
    "word": "બંને"
  },
  {
    "serial_number": 291,
    "word": "ચિહ્ન"
  },
  {
    "serial_number": 292,
    "word": "વારંવાર"
  },
  {
    "serial_number": 293,
    "word": "અક્ષર"
  },
  {
    "serial_number": 294,
    "word": "ત્યાં સુધી"
  },
  {
    "serial_number": 295,
    "word": "માઇલ"
  },
  {
    "serial_number": 296,
    "word": "નદી"
  },
  {
    "serial_number": 297,
    "word": "કાર"
  },
  {
    "serial_number": 298,
    "word": "પગ"
  },
  {
    "serial_number": 299,
    "word": "સંભાળ"
  },
  {
    "serial_number": 300,
    "word": "બીજા"
  },
  {
    "serial_number": 301,
    "word": "પર્યાપ્ત"
  },
  {
    "serial_number": 302,
    "word": "સાદા"
  },
  {
    "serial_number": 303,
    "word": "છોકરી"
  },
  {
    "serial_number": 304,
    "word": "સામાન્ય"
  },
  {
    "serial_number": 305,
    "word": "યુવાન"
  },
  {
    "serial_number": 306,
    "word": "તૈયાર"
  },
  {
    "serial_number": 307,
    "word": "ઉપર"
  },
  {
    "serial_number": 308,
    "word": "ક્યારેય"
  },
  {
    "serial_number": 309,
    "word": "લાલ"
  },
  {
    "serial_number": 310,
    "word": "યાદી"
  },
  {
    "serial_number": 311,
    "word": "છતાં"
  },
  {
    "serial_number": 312,
    "word": "લાગે"
  },
  {
    "serial_number": 313,
    "word": "ચર્ચા"
  },
  {
    "serial_number": 314,
    "word": "પક્ષી"
  },
  {
    "serial_number": 315,
    "word": "ટૂંક સમયમાં"
  },
  {
    "serial_number": 316,
    "word": "શરીર"
  },
  {
    "serial_number": 317,
    "word": "કૂતરો"
  },
  {
    "serial_number": 318,
    "word": "કુટુંબ"
  },
  {
    "serial_number": 319,
    "word": "સીધા"
  },
  {
    "serial_number": 320,
    "word": "દંભ"
  },
  {
    "serial_number": 321,
    "word": "છોડી"
  },
  {
    "serial_number": 322,
    "word": "ગીત"
  },
  {
    "serial_number": 323,
    "word": "માપવા"
  },
  {
    "serial_number": 324,
    "word": "બારણું"
  },
  {
    "serial_number": 325,
    "word": "ઉત્પાદન"
  },
  {
    "serial_number": 326,
    "word": "કાળા"
  },
  {
    "serial_number": 327,
    "word": "ટૂંકા"
  },
  {
    "serial_number": 328,
    "word": "આંકડો"
  },
  {
    "serial_number": 329,
    "word": "વર્ગ"
  },
  {
    "serial_number": 330,
    "word": "પવન"
  },
  {
    "serial_number": 331,
    "word": "પ્રશ્ન"
  },
  {
    "serial_number": 332,
    "word": "થાય"
  },
  {
    "serial_number": 333,
    "word": "પૂર્ણ"
  },
  {
    "serial_number": 334,
    "word": "જહાજ"
  },
  {
    "serial_number": 335,
    "word": "વિસ્તાર"
  },
  {
    "serial_number": 336,
    "word": "છ"
  },
  {
    "serial_number": 337,
    "word": "રોક"
  },
  {
    "serial_number": 338,
    "word": "માટે"
  },
  {
    "serial_number": 339,
    "word": "આગ"
  },
  {
    "serial_number": 340,
    "word": "દક્ષિણ"
  },
  {
    "serial_number": 341,
    "word": "સમસ્યા"
  },
  {
    "serial_number": 342,
    "word": "ભાગ"
  },
  {
    "serial_number": 343,
    "word": "જણાવ્યું"
  },
  {
    "serial_number": 344,
    "word": "જાણતા હતા"
  },
  {
    "serial_number": 345,
    "word": "પસાર"
  },
  {
    "serial_number": 346,
    "word": "કારણ"
  },
  {
    "serial_number": 347,
    "word": "ટોચ"
  },
  {
    "serial_number": 348,
    "word": "સમગ્ર"
  },
  {
    "serial_number": 349,
    "word": "રાજા"
  },
  {
    "serial_number": 350,
    "word": "શેરી"
  },
  {
    "serial_number": 351,
    "word": "ઇંચ"
  },
  {
    "serial_number": 352,
    "word": "ગુણાકાર"
  },
  {
    "serial_number": 353,
    "word": "કંઈ"
  },
  {
    "serial_number": 354,
    "word": "અલબત્ત"
  },
  {
    "serial_number": 355,
    "word": "રહેવા"
  },
  {
    "serial_number": 356,
    "word": "વ્હીલ"
  },
  {
    "serial_number": 357,
    "word": "સંપૂર્ણ"
  },
  {
    "serial_number": 358,
    "word": "બળ"
  },
  {
    "serial_number": 359,
    "word": "વાદળી"
  },
  {
    "serial_number": 360,
    "word": "પદાર્થ"
  },
  {
    "serial_number": 361,
    "word": "નક્કી"
  },
  {
    "serial_number": 362,
    "word": "સપાટી"
  },
  {
    "serial_number": 363,
    "word": "ઊંડા"
  },
  {
    "serial_number": 364,
    "word": "ચંદ્ર"
  },
  {
    "serial_number": 365,
    "word": "ટાપુ"
  },
  {
    "serial_number": 366,
    "word": "પગ"
  },
  {
    "serial_number": 367,
    "word": "સિસ્ટમ"
  },
  {
    "serial_number": 368,
    "word": "વ્યસ્ત"
  },
  {
    "serial_number": 369,
    "word": "ટેસ્ટ"
  },
  {
    "serial_number": 370,
    "word": "રેકોર્ડ"
  },
  {
    "serial_number": 371,
    "word": "હોડી"
  },
  {
    "serial_number": 372,
    "word": "સામાન્ય"
  },
  {
    "serial_number": 373,
    "word": "ગોલ્ડ"
  },
  {
    "serial_number": 374,
    "word": "શક્ય"
  },
  {
    "serial_number": 375,
    "word": "વિમાન"
  },
  {
    "serial_number": 376,
    "word": "સ્ટીડનો"
  },
  {
    "serial_number": 377,
    "word": "શુષ્ક"
  },
  {
    "serial_number": 378,
    "word": "આશ્ચર્ય"
  },
  {
    "serial_number": 379,
    "word": "હસે"
  },
  {
    "serial_number": 380,
    "word": "હજાર"
  },
  {
    "serial_number": 381,
    "word": "પહેલા"
  },
  {
    "serial_number": 382,
    "word": "ચાલી હતી"
  },
  {
    "serial_number": 383,
    "word": "તપાસ"
  },
  {
    "serial_number": 384,
    "word": "રમત"
  },
  {
    "serial_number": 385,
    "word": "આકાર"
  },
  {
    "serial_number": 386,
    "word": "સમીકરણ"
  },
  {
    "serial_number": 387,
    "word": "ગરમ"
  },
  {
    "serial_number": 388,
    "word": "ગુમ"
  },
  {
    "serial_number": 389,
    "word": "લાવ્યા"
  },
  {
    "serial_number": 390,
    "word": "ગરમી"
  },
  {
    "serial_number": 391,
    "word": "બરફ"
  },
  {
    "serial_number": 392,
    "word": "ટાયર"
  },
  {
    "serial_number": 393,
    "word": "લાવવા"
  },
  {
    "serial_number": 394,
    "word": "હા"
  },
  {
    "serial_number": 395,
    "word": "દૂરના"
  },
  {
    "serial_number": 396,
    "word": "ભરો"
  },
  {
    "serial_number": 397,
    "word": "પૂર્વ"
  },
  {
    "serial_number": 398,
    "word": "રંગ"
  },
  {
    "serial_number": 399,
    "word": "ભાષા"
  },
  {
    "serial_number": 400,
    "word": "વચ્ચે"
  },
  {
    "serial_number": 401,
    "word": "એકમ"
  },
  {
    "serial_number": 402,
    "word": "શક્તિ"
  },
  {
    "serial_number": 403,
    "word": "નગર"
  },
  {
    "serial_number": 404,
    "word": "દંડ"
  },
  {
    "serial_number": 405,
    "word": "ચોક્કસ"
  },
  {
    "serial_number": 406,
    "word": "ઉડાન"
  },
  {
    "serial_number": 407,
    "word": "આવતા"
  },
  {
    "serial_number": 408,
    "word": "દોરી"
  },
  {
    "serial_number": 409,
    "word": "કોલાહલ"
  },
  {
    "serial_number": 410,
    "word": "શ્યામ"
  },
  {
    "serial_number": 411,
    "word": "મશીન"
  },
  {
    "serial_number": 412,
    "word": "નોંધ"
  },
  {
    "serial_number": 413,
    "word": "રાહ"
  },
  {
    "serial_number": 414,
    "word": "યોજના"
  },
  {
    "serial_number": 415,
    "word": "આકૃતિ"
  },
  {
    "serial_number": 416,
    "word": "સ્ટાર"
  },
  {
    "serial_number": 417,
    "word": "બોક્સ"
  },
  {
    "serial_number": 418,
    "word": "નામ"
  },
  {
    "serial_number": 419,
    "word": "ક્ષેત્ર"
  },
  {
    "serial_number": 420,
    "word": "બાકીના"
  },
  {
    "serial_number": 421,
    "word": "યોગ્ય"
  },
  {
    "serial_number": 422,
    "word": "સક્ષમ"
  },
  {
    "serial_number": 423,
    "word": "પાઉન્ડ"
  },
  {
    "serial_number": 424,
    "word": "પૂર્ણ"
  },
  {
    "serial_number": 425,
    "word": "સુંદરતા"
  },
  {
    "serial_number": 426,
    "word": "ડ્રાઇવ"
  },
  {
    "serial_number": 427,
    "word": "હતી"
  },
  {
    "serial_number": 428,
    "word": "સમાવે"
  },
  {
    "serial_number": 429,
    "word": "સામે"
  },
  {
    "serial_number": 430,
    "word": "શીખવવા"
  },
  {
    "serial_number": 431,
    "word": "સપ્તાહ"
  },
  {
    "serial_number": 432,
    "word": "અંતિમ"
  },
  {
    "serial_number": 433,
    "word": "આપ્યો"
  },
  {
    "serial_number": 434,
    "word": "લીલા"
  },
  {
    "serial_number": 435,
    "word": "ઓહ"
  },
  {
    "serial_number": 436,
    "word": "ઝડપી"
  },
  {
    "serial_number": 437,
    "word": "વિકાસ"
  },
  {
    "serial_number": 438,
    "word": "સમુદ્ર"
  },
  {
    "serial_number": 439,
    "word": "ગરમ"
  },
  {
    "serial_number": 440,
    "word": "મફત"
  },
  {
    "serial_number": 441,
    "word": "મિનિટ"
  },
  {
    "serial_number": 442,
    "word": "મજબૂત"
  },
  {
    "serial_number": 443,
    "word": "ખાસ"
  },
  {
    "serial_number": 444,
    "word": "મન"
  },
  {
    "serial_number": 445,
    "word": "પાછળ"
  },
  {
    "serial_number": 446,
    "word": "પારદર્શક"
  },
  {
    "serial_number": 447,
    "word": "પૂંછડી"
  },
  {
    "serial_number": 448,
    "word": "ઉત્પાદન"
  },
  {
    "serial_number": 449,
    "word": "હકીકત"
  },
  {
    "serial_number": 450,
    "word": "જગ્યા"
  },
  {
    "serial_number": 451,
    "word": "સાંભળ્યું"
  },
  {
    "serial_number": 452,
    "word": "શ્રેષ્ઠ"
  },
  {
    "serial_number": 453,
    "word": "કલાક"
  },
  {
    "serial_number": 454,
    "word": "સારી"
  },
  {
    "serial_number": 455,
    "word": "સાચું"
  },
  {
    "serial_number": 456,
    "word": "દરમિયાન"
  },
  {
    "serial_number": 457,
    "word": "સો"
  },
  {
    "serial_number": 458,
    "word": "પાંચ"
  },
  {
    "serial_number": 459,
    "word": "યાદ"
  },
  {
    "serial_number": 460,
    "word": "પગલું"
  },
  {
    "serial_number": 461,
    "word": "પ્રારંભિક"
  },
  {
    "serial_number": 462,
    "word": "પકડી"
  },
  {
    "serial_number": 463,
    "word": "પશ્ચિમ"
  },
  {
    "serial_number": 464,
    "word": "જમીન"
  },
  {
    "serial_number": 465,
    "word": "રસ"
  },
  {
    "serial_number": 466,
    "word": "સુધી પહોંચવા"
  },
  {
    "serial_number": 467,
    "word": "ઝડપી"
  },
  {
    "serial_number": 468,
    "word": "ક્રિયાપદ"
  },
  {
    "serial_number": 469,
    "word": "ગાય"
  },
  {
    "serial_number": 470,
    "word": "સાંભળવા"
  },
  {
    "serial_number": 471,
    "word": "છ"
  },
  {
    "serial_number": 472,
    "word": "ટેબલ"
  },
  {
    "serial_number": 473,
    "word": "પ્રવાસ"
  },
  {
    "serial_number": 474,
    "word": "ઓછી"
  },
  {
    "serial_number": 475,
    "word": "સવારે"
  },
  {
    "serial_number": 476,
    "word": "દસ"
  },
  {
    "serial_number": 477,
    "word": "સરળ"
  },
  {
    "serial_number": 478,
    "word": "અનેક"
  },
  {
    "serial_number": 479,
    "word": "સ્વર"
  },
  {
    "serial_number": 480,
    "word": "તરફ"
  },
  {
    "serial_number": 481,
    "word": "યુદ્ધ"
  },
  {
    "serial_number": 482,
    "word": "મૂકે"
  },
  {
    "serial_number": 483,
    "word": "સામે"
  },
  {
    "serial_number": 484,
    "word": "પેટર્ન"
  },
  {
    "serial_number": 485,
    "word": "ધીમી"
  },
  {
    "serial_number": 486,
    "word": "કેન્દ્ર"
  },
  {
    "serial_number": 487,
    "word": "પ્રેમ"
  },
  {
    "serial_number": 488,
    "word": "વ્યક્તિ"
  },
  {
    "serial_number": 489,
    "word": "પૈસા"
  },
  {
    "serial_number": 490,
    "word": "સેવા આપવા"
  },
  {
    "serial_number": 491,
    "word": "દેખાય"
  },
  {
    "serial_number": 492,
    "word": "માર્ગ"
  },
  {
    "serial_number": 493,
    "word": "નકશો"
  },
  {
    "serial_number": 494,
    "word": "વરસાદ"
  },
  {
    "serial_number": 495,
    "word": "નિયમ"
  },
  {
    "serial_number": 496,
    "word": "સંચાલન"
  },
  {
    "serial_number": 497,
    "word": "ખેંચી"
  },
  {
    "serial_number": 498,
    "word": "ઠંડા"
  },
  {
    "serial_number": 499,
    "word": "નોટિસ"
  },
  {
    "serial_number": 500,
    "word": "અવાજ"
  },
  {
    "serial_number": 501,
    "word": "ઊર્જા"
  },
  {
    "serial_number": 502,
    "word": "શિકાર"
  },
  {
    "serial_number": 503,
    "word": "સંભવિત"
  },
  {
    "serial_number": 504,
    "word": "બેડ"
  },
  {
    "serial_number": 505,
    "word": "ભાઈ"
  },
  {
    "serial_number": 506,
    "word": "ઇંડા"
  },
  {
    "serial_number": 507,
    "word": "સવારી"
  },
  {
    "serial_number": 508,
    "word": "સેલ"
  },
  {
    "serial_number": 509,
    "word": "માને"
  },
  {
    "serial_number": 510,
    "word": "કદાચ"
  },
  {
    "serial_number": 511,
    "word": "પસંદ"
  },
  {
    "serial_number": 512,
    "word": "અચાનક"
  },
  {
    "serial_number": 513,
    "word": "ગણતરી"
  },
  {
    "serial_number": 514,
    "word": "ચોરસ"
  },
  {
    "serial_number": 515,
    "word": "કારણ"
  },
  {
    "serial_number": 516,
    "word": "લંબાઈ"
  },
  {
    "serial_number": 517,
    "word": "પ્રતિનિધિત્વ"
  },
  {
    "serial_number": 518,
    "word": "કલા"
  },
  {
    "serial_number": 519,
    "word": "વિષય"
  },
  {
    "serial_number": 520,
    "word": "પ્રદેશ"
  },
  {
    "serial_number": 521,
    "word": "કદ"
  },
  {
    "serial_number": 522,
    "word": "અલગ અલગ હોય છે"
  },
  {
    "serial_number": 523,
    "word": "પતાવટ"
  },
  {
    "serial_number": 524,
    "word": "વાત"
  },
  {
    "serial_number": 525,
    "word": "વજન"
  },
  {
    "serial_number": 526,
    "word": "સામાન્ય"
  },
  {
    "serial_number": 527,
    "word": "બરફ"
  },
  {
    "serial_number": 528,
    "word": "બાબત"
  },
  {
    "serial_number": 529,
    "word": "વર્તુળ"
  },
  {
    "serial_number": 530,
    "word": "જોડી"
  },
  {
    "serial_number": 531,
    "word": "સમાવેશ થાય છે"
  },
  {
    "serial_number": 532,
    "word": "વિભાજન"
  },
  {
    "serial_number": 533,
    "word": "ઉચ્ચારણ"
  },
  {
    "serial_number": 534,
    "word": "લાગ્યું"
  },
  {
    "serial_number": 535,
    "word": "ગ્રાન્ડ"
  },
  {
    "serial_number": 536,
    "word": "બોલ"
  },
  {
    "serial_number": 537,
    "word": "હજુ સુધી"
  },
  {
    "serial_number": 538,
    "word": "તરંગ"
  },
  {
    "serial_number": 539,
    "word": "છોડો"
  },
  {
    "serial_number": 540,
    "word": "હૃદય"
  },
  {
    "serial_number": 541,
    "word": "છું"
  },
  {
    "serial_number": 542,
    "word": "હાજર"
  },
  {
    "serial_number": 543,
    "word": "ભારે"
  },
  {
    "serial_number": 544,
    "word": "નૃત્ય"
  },
  {
    "serial_number": 545,
    "word": "એન્જિન"
  },
  {
    "serial_number": 546,
    "word": "સ્થિતિ"
  },
  {
    "serial_number": 547,
    "word": "હાથ"
  },
  {
    "serial_number": 548,
    "word": "વિશાળ"
  },
  {
    "serial_number": 549,
    "word": "સઢ"
  },
  {
    "serial_number": 550,
    "word": "સામગ્રી"
  },
  {
    "serial_number": 551,
    "word": "અપૂર્ણાંક"
  },
  {
    "serial_number": 552,
    "word": "વન"
  },
  {
    "serial_number": 553,
    "word": "બેસી"
  },
  {
    "serial_number": 554,
    "word": "રેસ"
  },
  {
    "serial_number": 555,
    "word": "વિન્ડો"
  },
  {
    "serial_number": 556,
    "word": "સ્ટોર"
  },
  {
    "serial_number": 557,
    "word": "ઉનાળામાં"
  },
  {
    "serial_number": 558,
    "word": "ટ્રેન"
  },
  {
    "serial_number": 559,
    "word": "ઊંઘ"
  },
  {
    "serial_number": 560,
    "word": "સાબિત"
  },
  {
    "serial_number": 561,
    "word": "એકલા"
  },
  {
    "serial_number": 562,
    "word": "બોલ"
  },
  {
    "serial_number": 563,
    "word": "કસરત"
  },
  {
    "serial_number": 564,
    "word": "દિવાલ"
  },
  {
    "serial_number": 565,
    "word": "કેચ"
  },
  {
    "serial_number": 566,
    "word": "માઉન્ટ"
  },
  {
    "serial_number": 567,
    "word": "માંગો"
  },
  {
    "serial_number": 568,
    "word": "આકાશ"
  },
  {
    "serial_number": 569,
    "word": "બોર્ડ"
  },
  {
    "serial_number": 570,
    "word": "આનંદ"
  },
  {
    "serial_number": 571,
    "word": "શિયાળામાં"
  },
  {
    "serial_number": 572,
    "word": "શનિ"
  },
  {
    "serial_number": 573,
    "word": "લખવામાં"
  },
  {
    "serial_number": 574,
    "word": "જંગલી"
  },
  {
    "serial_number": 575,
    "word": "સાધન"
  },
  {
    "serial_number": 576,
    "word": "રાખવામાં"
  },
  {
    "serial_number": 577,
    "word": "કાચ"
  },
  {
    "serial_number": 578,
    "word": "ઘાસ"
  },
  {
    "serial_number": 579,
    "word": "ગાય"
  },
  {
    "serial_number": 580,
    "word": "કામ"
  },
  {
    "serial_number": 581,
    "word": "ધાર"
  },
  {
    "serial_number": 582,
    "word": "સાઇન"
  },
  {
    "serial_number": 583,
    "word": "મુલાકાત"
  },
  {
    "serial_number": 584,
    "word": "છેલ્લા"
  },
  {
    "serial_number": 585,
    "word": "નરમ"
  },
  {
    "serial_number": 586,
    "word": "મજા"
  },
  {
    "serial_number": 587,
    "word": "તેજસ્વી"
  },
  {
    "serial_number": 588,
    "word": "ગેસ"
  },
  {
    "serial_number": 589,
    "word": "હવામાન"
  },
  {
    "serial_number": 590,
    "word": "મહિનો"
  },
  {
    "serial_number": 591,
    "word": "મિલિયન"
  },
  {
    "serial_number": 592,
    "word": "સહન"
  },
  {
    "serial_number": 593,
    "word": "સમાપ્ત"
  },
  {
    "serial_number": 594,
    "word": "સુખી"
  },
  {
    "serial_number": 595,
    "word": "આશા"
  },
  {
    "serial_number": 596,
    "word": "ફૂલ"
  },
  {
    "serial_number": 597,
    "word": "વસ્ત્રની"
  },
  {
    "serial_number": 598,
    "word": "વિચિત્ર"
  },
  {
    "serial_number": 599,
    "word": "ગયો"
  },
  {
    "serial_number": 600,
    "word": "વેપાર"
  },
  {
    "serial_number": 601,
    "word": "મેલોડી"
  },
  {
    "serial_number": 602,
    "word": "પ્રવાસ"
  },
  {
    "serial_number": 603,
    "word": "ઓફિસ"
  },
  {
    "serial_number": 604,
    "word": "પ્રાપ્ત"
  },
  {
    "serial_number": 605,
    "word": "પંક્તિ"
  },
  {
    "serial_number": 606,
    "word": "મોં"
  },
  {
    "serial_number": 607,
    "word": "ચોક્કસ"
  },
  {
    "serial_number": 608,
    "word": "પ્રતીક"
  },
  {
    "serial_number": 609,
    "word": "મૃત્યુ પામે છે"
  },
  {
    "serial_number": 610,
    "word": "ઓછા"
  },
  {
    "serial_number": 611,
    "word": "મુશ્કેલી"
  },
  {
    "serial_number": 612,
    "word": "પાડો"
  },
  {
    "serial_number": 613,
    "word": "સિવાય"
  },
  {
    "serial_number": 614,
    "word": "લખ્યું"
  },
  {
    "serial_number": 615,
    "word": "બીજ"
  },
  {
    "serial_number": 616,
    "word": "સ્વર"
  },
  {
    "serial_number": 617,
    "word": "જોડાવા"
  },
  {
    "serial_number": 618,
    "word": "સૂચવે છે"
  },
  {
    "serial_number": 619,
    "word": "સ્વચ્છ"
  },
  {
    "serial_number": 620,
    "word": "વિરામ"
  },
  {
    "serial_number": 621,
    "word": "મહિલા"
  },
  {
    "serial_number": 622,
    "word": "યાર્ડ"
  },
  {
    "serial_number": 623,
    "word": "વધારો"
  },
  {
    "serial_number": 624,
    "word": "ખરાબ"
  },
  {
    "serial_number": 625,
    "word": "ફટકો"
  },
  {
    "serial_number": 626,
    "word": "તેલ"
  },
  {
    "serial_number": 627,
    "word": "રક્ત"
  },
  {
    "serial_number": 628,
    "word": "સ્પર્શ"
  },
  {
    "serial_number": 629,
    "word": "વધારો થયો હતો"
  },
  {
    "serial_number": 630,
    "word": "ટકા"
  },
  {
    "serial_number": 631,
    "word": "મિશ્રણ"
  },
  {
    "serial_number": 632,
    "word": "ટીમ"
  },
  {
    "serial_number": 633,
    "word": "વાયર"
  },
  {
    "serial_number": 634,
    "word": "ખર્ચ"
  },
  {
    "serial_number": 635,
    "word": "ગુમાવી"
  },
  {
    "serial_number": 636,
    "word": "બદામી"
  },
  {
    "serial_number": 637,
    "word": "ભાષા"
  },
  {
    "serial_number": 638,
    "word": "બગીચો"
  },
  {
    "serial_number": 639,
    "word": "સમાન"
  },
  {
    "serial_number": 640,
    "word": "મોકલવામાં"
  },
  {
    "serial_number": 641,
    "word": "પસંદ"
  },
  {
    "serial_number": 642,
    "word": "હતો"
  },
  {
    "serial_number": 643,
    "word": "ફિટ"
  },
  {
    "serial_number": 644,
    "word": "પ્રવાહ"
  },
  {
    "serial_number": 645,
    "word": "વાજબી"
  },
  {
    "serial_number": 646,
    "word": "બેંક"
  },
  {
    "serial_number": 647,
    "word": "એકત્રિત"
  },
  {
    "serial_number": 648,
    "word": "સેવ"
  },
  {
    "serial_number": 649,
    "word": "નિયંત્રણ"
  },
  {
    "serial_number": 650,
    "word": "બાદ"
  },
  {
    "serial_number": 651,
    "word": "કાન"
  },
  {
    "serial_number": 652,
    "word": "અન્ય"
  },
  {
    "serial_number": 653,
    "word": "તદ્દન"
  },
  {
    "serial_number": 654,
    "word": "તોડી"
  },
  {
    "serial_number": 655,
    "word": "કેસ"
  },
  {
    "serial_number": 656,
    "word": "મધ્યમ"
  },
  {
    "serial_number": 657,
    "word": "મારી"
  },
  {
    "serial_number": 658,
    "word": "પુત્ર"
  },
  {
    "serial_number": 659,
    "word": "તળાવ"
  },
  {
    "serial_number": 660,
    "word": "ક્ષણ"
  },
  {
    "serial_number": 661,
    "word": "સ્કેલ"
  },
  {
    "serial_number": 662,
    "word": "મોટા"
  },
  {
    "serial_number": 663,
    "word": "વસંત"
  },
  {
    "serial_number": 664,
    "word": "અવલોકન"
  },
  {
    "serial_number": 665,
    "word": "બાળક"
  },
  {
    "serial_number": 666,
    "word": "કોઈ રન નોંધાયો નહીં"
  },
  {
    "serial_number": 667,
    "word": "વ્યંજન"
  },
  {
    "serial_number": 668,
    "word": "રાષ્ટ્ર"
  },
  {
    "serial_number": 669,
    "word": "શબ્દકોશ"
  },
  {
    "serial_number": 670,
    "word": "દૂધ"
  },
  {
    "serial_number": 671,
    "word": "ઝડપ"
  },
  {
    "serial_number": 672,
    "word": "પદ્ધતિ"
  },
  {
    "serial_number": 673,
    "word": "અંગ"
  },
  {
    "serial_number": 674,
    "word": "ચૂકવણી"
  },
  {
    "serial_number": 675,
    "word": "ઉંમર"
  },
  {
    "serial_number": 676,
    "word": "વિભાગ"
  },
  {
    "serial_number": 677,
    "word": "ડ્રેસ"
  },
  {
    "serial_number": 678,
    "word": "વાદળું"
  },
  {
    "serial_number": 679,
    "word": "આશ્ચર્ય"
  },
  {
    "serial_number": 680,
    "word": "શાંત"
  },
  {
    "serial_number": 681,
    "word": "પથ્થર"
  },
  {
    "serial_number": 682,
    "word": "નાના"
  },
  {
    "serial_number": 683,
    "word": "ચઢી"
  },
  {
    "serial_number": 684,
    "word": "ઠંડી"
  },
  {
    "serial_number": 685,
    "word": "ડિઝાઇન"
  },
  {
    "serial_number": 686,
    "word": "ગરીબ"
  },
  {
    "serial_number": 687,
    "word": "ઘણો"
  },
  {
    "serial_number": 688,
    "word": "પ્રયોગ"
  },
  {
    "serial_number": 689,
    "word": "નીચે"
  },
  {
    "serial_number": 690,
    "word": "કી"
  },
  {
    "serial_number": 691,
    "word": "લોખંડ"
  },
  {
    "serial_number": 692,
    "word": "એક"
  },
  {
    "serial_number": 693,
    "word": "લાકડી"
  },
  {
    "serial_number": 694,
    "word": "ફ્લેટ"
  },
  {
    "serial_number": 695,
    "word": "વીસ"
  },
  {
    "serial_number": 696,
    "word": "ત્વચા"
  },
  {
    "serial_number": 697,
    "word": "સ્મિત"
  },
  {
    "serial_number": 698,
    "word": "બોલ"
  },
  {
    "serial_number": 699,
    "word": "છિદ્ર"
  },
  {
    "serial_number": 700,
    "word": "આવો"
  },
  {
    "serial_number": 701,
    "word": "બાળક"
  },
  {
    "serial_number": 702,
    "word": "આઠ"
  },
  {
    "serial_number": 703,
    "word": "ગામ"
  },
  {
    "serial_number": 704,
    "word": "પૂરી"
  },
  {
    "serial_number": 705,
    "word": "રુટ"
  },
  {
    "serial_number": 706,
    "word": "ખરીદી"
  },
  {
    "serial_number": 707,
    "word": "એકત્ર"
  },
  {
    "serial_number": 708,
    "word": "હલ"
  },
  {
    "serial_number": 709,
    "word": "મેટલ"
  },
  {
    "serial_number": 710,
    "word": "કે શું"
  },
  {
    "serial_number": 711,
    "word": "દબાણ"
  },
  {
    "serial_number": 712,
    "word": "સાત"
  },
  {
    "serial_number": 713,
    "word": "ફકરો"
  },
  {
    "serial_number": 714,
    "word": "ત્રીજા"
  },
  {
    "serial_number": 715,
    "word": "રહેશે"
  },
  {
    "serial_number": 716,
    "word": "આયોજન"
  },
  {
    "serial_number": 717,
    "word": "વાળ"
  },
  {
    "serial_number": 718,
    "word": "વર્ણન"
  },
  {
    "serial_number": 719,
    "word": "રસોઈયા"
  },
  {
    "serial_number": 720,
    "word": "માળ"
  },
  {
    "serial_number": 721,
    "word": "ક્યાં"
  },
  {
    "serial_number": 722,
    "word": "પરિણામ"
  },
  {
    "serial_number": 723,
    "word": "બર્ન"
  },
  {
    "serial_number": 724,
    "word": "હિલ"
  },
  {
    "serial_number": 725,
    "word": "સલામત"
  },
  {
    "serial_number": 726,
    "word": "બિલાડી"
  },
  {
    "serial_number": 727,
    "word": "સદી"
  },
  {
    "serial_number": 728,
    "word": "ધ્યાનમાં"
  },
  {
    "serial_number": 729,
    "word": "પ્રકાર"
  },
  {
    "serial_number": 730,
    "word": "કાયદો"
  },
  {
    "serial_number": 731,
    "word": "બીટ"
  },
  {
    "serial_number": 732,
    "word": "કિનારે"
  },
  {
    "serial_number": 733,
    "word": "નકલ"
  },
  {
    "serial_number": 734,
    "word": "મહાવરો"
  },
  {
    "serial_number": 735,
    "word": "શાંત"
  },
  {
    "serial_number": 736,
    "word": "ઊંચા"
  },
  {
    "serial_number": 737,
    "word": "રેતી"
  },
  {
    "serial_number": 738,
    "word": "જમીન"
  },
  {
    "serial_number": 739,
    "word": "રોલ"
  },
  {
    "serial_number": 740,
    "word": "તાપમાન"
  },
  {
    "serial_number": 741,
    "word": "આંગળી"
  },
  {
    "serial_number": 742,
    "word": "ઉદ્યોગ"
  },
  {
    "serial_number": 743,
    "word": "કિંમત"
  },
  {
    "serial_number": 744,
    "word": "લડાઈ"
  },
  {
    "serial_number": 745,
    "word": "અસત્ય"
  },
  {
    "serial_number": 746,
    "word": "હરાવ્યું"
  },
  {
    "serial_number": 747,
    "word": "ઉત્તેજિત"
  },
  {
    "serial_number": 748,
    "word": "કુદરતી"
  },
  {
    "serial_number": 749,
    "word": "દૃશ્ય"
  },
  {
    "serial_number": 750,
    "word": "અર્થમાં"
  },
  {
    "serial_number": 751,
    "word": "મૂડી"
  },
  {
    "serial_number": 752,
    "word": "નહીં"
  },
  {
    "serial_number": 753,
    "word": "ખુરશી"
  },
  {
    "serial_number": 754,
    "word": "ભય"
  },
  {
    "serial_number": 755,
    "word": "ફળ"
  },
  {
    "serial_number": 756,
    "word": "સમૃદ્ધ"
  },
  {
    "serial_number": 757,
    "word": "જાડા"
  },
  {
    "serial_number": 758,
    "word": "સૈનિક"
  },
  {
    "serial_number": 759,
    "word": "પ્રક્રિયા"
  },
  {
    "serial_number": 760,
    "word": "કામ"
  },
  {
    "serial_number": 761,
    "word": "પ્રથા"
  },
  {
    "serial_number": 762,
    "word": "અલગ"
  },
  {
    "serial_number": 763,
    "word": "મુશ્કેલ"
  },
  {
    "serial_number": 764,
    "word": "ડૉક્ટર"
  },
  {
    "serial_number": 765,
    "word": "કૃપા કરીને"
  },
  {
    "serial_number": 766,
    "word": "રક્ષણ"
  },
  {
    "serial_number": 767,
    "word": "બપોરે"
  },
  {
    "serial_number": 768,
    "word": "પાક"
  },
  {
    "serial_number": 769,
    "word": "આધુનિક"
  },
  {
    "serial_number": 770,
    "word": "તત્વ"
  },
  {
    "serial_number": 771,
    "word": "હિટ"
  },
  {
    "serial_number": 772,
    "word": "વિદ્યાર્થી"
  },
  {
    "serial_number": 773,
    "word": "ખૂણે"
  },
  {
    "serial_number": 774,
    "word": "પક્ષ"
  },
  {
    "serial_number": 775,
    "word": "પુરવઠો"
  },
  {
    "serial_number": 776,
    "word": "જેના"
  },
  {
    "serial_number": 777,
    "word": "સ્થિત"
  },
  {
    "serial_number": 778,
    "word": "રિંગ"
  },
  {
    "serial_number": 779,
    "word": "પાત્ર"
  },
  {
    "serial_number": 780,
    "word": "જંતુ"
  },
  {
    "serial_number": 781,
    "word": "કેચ"
  },
  {
    "serial_number": 782,
    "word": "સમય"
  },
  {
    "serial_number": 783,
    "word": "સૂચવે છે"
  },
  {
    "serial_number": 784,
    "word": "રેડિયો"
  },
  {
    "serial_number": 785,
    "word": "વાત કરી હતી"
  },
  {
    "serial_number": 786,
    "word": "અણુ"
  },
  {
    "serial_number": 787,
    "word": "માનવ"
  },
  {
    "serial_number": 788,
    "word": "ઇતિહાસ"
  },
  {
    "serial_number": 789,
    "word": "અસર"
  },
  {
    "serial_number": 790,
    "word": "ઇલેક્ટ્રિક"
  },
  {
    "serial_number": 791,
    "word": "અપેક્ષા"
  },
  {
    "serial_number": 792,
    "word": "અસ્થિ"
  },
  {
    "serial_number": 793,
    "word": "રેલવે"
  },
  {
    "serial_number": 794,
    "word": "કલ્પના"
  },
  {
    "serial_number": 795,
    "word": "પૂરી પાડે છે"
  },
  {
    "serial_number": 796,
    "word": "સંમત"
  },
  {
    "serial_number": 797,
    "word": "આમ"
  },
  {
    "serial_number": 798,
    "word": "સૌમ્ય"
  },
  {
    "serial_number": 799,
    "word": "મહિલા"
  },
  {
    "serial_number": 800,
    "word": "કેપ્ટન"
  },
  {
    "serial_number": 801,
    "word": "ધારી"
  },
  {
    "serial_number": 802,
    "word": "જરૂરી"
  },
  {
    "serial_number": 803,
    "word": "તીવ્ર"
  },
  {
    "serial_number": 804,
    "word": "પાંખ"
  },
  {
    "serial_number": 805,
    "word": "બનાવો"
  },
  {
    "serial_number": 806,
    "word": "પાડોશી"
  },
  {
    "serial_number": 807,
    "word": "ધોવું"
  },
  {
    "serial_number": 808,
    "word": "બેટ"
  },
  {
    "serial_number": 809,
    "word": "બદલે"
  },
  {
    "serial_number": 810,
    "word": "ભીડ"
  },
  {
    "serial_number": 811,
    "word": "મકાઈ"
  },
  {
    "serial_number": 812,
    "word": "સરખામણી"
  },
  {
    "serial_number": 813,
    "word": "કવિતા"
  },
  {
    "serial_number": 814,
    "word": "શબ્દમાળા"
  },
  {
    "serial_number": 815,
    "word": "ઘંટડી"
  },
  {
    "serial_number": 816,
    "word": "આધાર રાખે છે"
  },
  {
    "serial_number": 817,
    "word": "માંસ"
  },
  {
    "serial_number": 818,
    "word": "ઘસવું"
  },
  {
    "serial_number": 819,
    "word": "ટ્યુબ"
  },
  {
    "serial_number": 820,
    "word": "વિખ્યાત"
  },
  {
    "serial_number": 921,
    "word": "ડોલર"
  },
  {
    "serial_number": 822,
    "word": "સ્ટ્રીમ"
  },
  {
    "serial_number": 823,
    "word": "ભય"
  },
  {
    "serial_number": 284,
    "word": "દૃષ્ટિ"
  },
  {
    "serial_number": 825,
    "word": "પાતળા"
  },
  {
    "serial_number": 826,
    "word": "ત્રિકોણ"
  },
  {
    "serial_number": 827,
    "word": "ગ્રહ"
  },
  {
    "serial_number": 828,
    "word": "ઉતાવળ કરવી"
  },
  {
    "serial_number": 829,
    "word": "મુખ્ય"
  },
  {
    "serial_number": 830,
    "word": "વસાહત"
  },
  {
    "serial_number": 831,
    "word": "ઘડિયાળ"
  },
  {
    "serial_number": 832,
    "word": "ખાણ"
  },
  {
    "serial_number": 833,
    "word": "ટાઇ"
  },
  {
    "serial_number": 834,
    "word": "દાખલ"
  },
  {
    "serial_number": 835,
    "word": "મુખ્ય"
  },
  {
    "serial_number": 836,
    "word": "તાજા"
  },
  {
    "serial_number": 837,
    "word": "શોધ"
  },
  {
    "serial_number": 838,
    "word": "મોકલવા"
  },
  {
    "serial_number": 839,
    "word": "પીળા"
  },
  {
    "serial_number": 840,
    "word": "બંદૂક"
  },
  {
    "serial_number": 841,
    "word": "પરવાનગી"
  },
  {
    "serial_number": 842,
    "word": "પ્રિન્ટ"
  },
  {
    "serial_number": 843,
    "word": "મૃત"
  },
  {
    "serial_number": 844,
    "word": "હાજર"
  },
  {
    "serial_number": 845,
    "word": "રણ"
  },
  {
    "serial_number": 846,
    "word": "દાવો"
  },
  {
    "serial_number": 847,
    "word": "વર્તમાન"
  },
  {
    "serial_number": 848,
    "word": "લિફ્ટ"
  },
  {
    "serial_number": 840,
    "word": "ગુલાબ"
  },
  {
    "serial_number": 850,
    "word": "આવો"
  },
  {
    "serial_number": 851,
    "word": "માસ્ટર"
  },
  {
    "serial_number": 852,
    "word": "ટ્રેક"
  },
  {
    "serial_number": 853,
    "word": "પિતૃ"
  },
  {
    "serial_number": 854,
    "word": "કિનારા"
  },
  {
    "serial_number": 855,
    "word": "વિભાગ"
  },
  {
    "serial_number": 856,
    "word": "શીટ"
  },
  {
    "serial_number": 857,
    "word": "પદાર્થ"
  },
  {
    "serial_number": 858,
    "word": "તરફેણ"
  },
  {
    "serial_number": 859,
    "word": "કનેક્ટ"
  },
  {
    "serial_number": 860,
    "word": "પોસ્ટ"
  },
  {
    "serial_number": 861,
    "word": "ખર્ચ"
  },
  {
    "serial_number": 862,
    "word": "તાર"
  },
  {
    "serial_number": 863,
    "word": "ચરબી"
  },
  {
    "serial_number": 864,
    "word": "ખુશી"
  },
  {
    "serial_number": 865,
    "word": "મૂળ"
  },
  {
    "serial_number": 866,
    "word": "શેર"
  },
  {
    "serial_number": 867,
    "word": "સ્ટેશન"
  },
  {
    "serial_number": 868,
    "word": "પિતા"
  },
  {
    "serial_number": 869,
    "word": "બ્રેડ"
  },
  {
    "serial_number": 870,
    "word": "ચાર્જ"
  },
  {
    "serial_number": 871,
    "word": "યોગ્ય"
  },
  {
    "serial_number": 872,
    "word": "બાર"
  },
  {
    "serial_number": 873,
    "word": "ઓફર"
  },
  {
    "serial_number": 874,
    "word": "સેગમેન્ટમાં"
  },
  {
    "serial_number": 875,
    "word": "ગુલામ"
  },
  {
    "serial_number": 876,
    "word": "બતક"
  },
  {
    "serial_number": 877,
    "word": "ઇન્સ્ટન્ટ"
  },
  {
    "serial_number": 878,
    "word": "બજાર"
  },
  {
    "serial_number": 879,
    "word": "ડિગ્રી"
  },
  {
    "serial_number": 880,
    "word": "રચના"
  },
  {
    "serial_number": 881,
    "word": "પક્ષીનું બચ્ચું"
  },
  {
    "serial_number": 882,
    "word": "પ્રિય"
  },
  {
    "serial_number": 883,
    "word": "દુશ્મન"
  },
  {
    "serial_number": 884,
    "word": "જવાબ"
  },
  {
    "serial_number": 885,
    "word": "પીણું"
  },
  {
    "serial_number": 886,
    "word": "થાય"
  },
  {
    "serial_number": 887,
    "word": "આધાર"
  },
  {
    "serial_number": 888,
    "word": "ભાષણ"
  },
  {
    "serial_number": 889,
    "word": "પ્રકૃતિ"
  },
  {
    "serial_number": 890,
    "word": "શ્રેણી"
  },
  {
    "serial_number": 891,
    "word": "વરાળ"
  },
  {
    "serial_number": 892,
    "word": "ગતિ"
  },
  {
    "serial_number": 893,
    "word": "પાથ"
  },
  {
    "serial_number": 894,
    "word": "પ્રવાહી"
  },
  {
    "serial_number": 895,
    "word": "લોગ"
  },
  {
    "serial_number": 896,
    "word": "અર્થ"
  },
  {
    "serial_number": 897,
    "word": "આંક"
  },
  {
    "serial_number": 898,
    "word": "દાંત"
  },
  {
    "serial_number": 899,
    "word": "શેલ"
  },
  {
    "serial_number": 900,
    "word": "ગરદન"
  },
  {
    "serial_number": 901,
    "word": "ઓક્સિજન"
  },
  {
    "serial_number": 902,
    "word": "ખાંડ"
  },
  {
    "serial_number": 903,
    "word": "મૃત્યુ"
  },
  {
    "serial_number": 904,
    "word": "ખૂબ"
  },
  {
    "serial_number": 905,
    "word": "કૌશલ્ય"
  },
  {
    "serial_number": 906,
    "word": "સ્ત્રીઓ"
  },
  {
    "serial_number": 907,
    "word": "મોસમ"
  },
  {
    "serial_number": 908,
    "word": "ઉકેલ"
  },
  {
    "serial_number": 909,
    "word": "ચુંબક"
  },
  {
    "serial_number": 910,
    "word": "ચાંદીના"
  },
  {
    "serial_number": 911,
    "word": "આભાર"
  },
  {
    "serial_number": 912,
    "word": "શાખા"
  },
  {
    "serial_number": 913,
    "word": "મેચ"
  },
  {
    "serial_number": 914,
    "word": "પ્રત્યય"
  },
  {
    "serial_number": 915,
    "word": "ખાસ કરીને"
  },
  {
    "serial_number": 916,
    "word": "અંજીર"
  },
  {
    "serial_number": 917,
    "word": "ભયભીત"
  },
  {
    "serial_number": 918,
    "word": "વિશાળ"
  },
  {
    "serial_number": 919,
    "word": "બહેન"
  },
  {
    "serial_number": 920,
    "word": "સ્ટીલ"
  },
  {
    "serial_number": 921,
    "word": "ચર્ચા"
  },
  {
    "serial_number": 922,
    "word": "આગળ"
  },
  {
    "serial_number": 923,
    "word": "સમાન"
  },
  {
    "serial_number": 924,
    "word": "માર્ગદર્શન"
  },
  {
    "serial_number": 925,
    "word": "અનુભવ"
  },
  {
    "serial_number": 926,
    "word": "સ્કોર"
  },
  {
    "serial_number": 927,
    "word": "સફરજન"
  },
  {
    "serial_number": 928,
    "word": "ખરીદી"
  },
  {
    "serial_number": 929,
    "word": "દોરી"
  },
  {
    "serial_number": 930,
    "word": "પિચ"
  },
  {
    "serial_number": 931,
    "word": "કોટ"
  },
  {
    "serial_number": 932,
    "word": "સમૂહ"
  },
  {
    "serial_number": 933,
    "word": "કાર્ડ"
  },
  {
    "serial_number": 934,
    "word": "બેન્ડ"
  },
  {
    "serial_number": 935,
    "word": "દોરડું"
  },
  {
    "serial_number": 936,
    "word": "કાપલી"
  },
  {
    "serial_number": 937,
    "word": "જીત"
  },
  {
    "serial_number": 938,
    "word": "સ્વપ્ન"
  },
  {
    "serial_number": 939,
    "word": "સાંજે"
  },
  {
    "serial_number": 940,
    "word": "સ્થિતિ"
  },
  {
    "serial_number": 941,
    "word": "ફીડ"
  },
  {
    "serial_number": 942,
    "word": "સાધન"
  },
  {
    "serial_number": 943,
    "word": "કુલ"
  },
  {
    "serial_number": 944,
    "word": "મૂળભૂત"
  },
  {
    "serial_number": 945,
    "word": "ગંધ"
  },
  {
    "serial_number": 946,
    "word": "ખીણ"
  },
  {
    "serial_number": 947,
    "word": "કે"
  },
  {
    "serial_number": 948,
    "word": "ડબલ"
  },
  {
    "serial_number": 949,
    "word": "બેઠક"
  },
  {
    "serial_number": 950,
    "word": "ચાલુ"
  },
  {
    "serial_number": 951,
    "word": "બ્લોક"
  },
  {
    "serial_number": 952,
    "word": "ચાર્ટ"
  },
  {
    "serial_number": 953,
    "word": "ટોપી"
  },
  {
    "serial_number": 954,
    "word": "વેચાણ"
  },
  {
    "serial_number": 955,
    "word": "સફળતા"
  },
  {
    "serial_number": 956,
    "word": "કંપની"
  },
  {
    "serial_number": 957,
    "word": "બાદબાકી"
  },
  {
    "serial_number": 958,
    "word": "ઘટના"
  },
  {
    "serial_number": 959,
    "word": "ખાસ"
  },
  {
    "serial_number": 960,
    "word": "સોદો"
  },
  {
    "serial_number": 961,
    "word": "તરી"
  },
  {
    "serial_number": 962,
    "word": "શબ્દ"
  },
  {
    "serial_number": 963,
    "word": "વિરુદ્ધ"
  },
  {
    "serial_number": 964,
    "word": "પત્ની"
  },
  {
    "serial_number": 965,
    "word": "જૂતા"
  },
  {
    "serial_number": 966,
    "word": "ખભા"
  },
  {
    "serial_number": 967,
    "word": "ફેલાવો"
  },
  {
    "serial_number": 968,
    "word": "વ્યવસ્થા"
  },
  {
    "serial_number": 969,
    "word": "શિબિર"
  },
  {
    "serial_number": 970,
    "word": "શોધ"
  },
  {
    "serial_number": 971,
    "word": "કપાસ"
  },
  {
    "serial_number": 972,
    "word": "બોર્ન"
  },
  {
    "serial_number": 973,
    "word": "નક્કી"
  },
  {
    "serial_number": 974,
    "word": "પા ગેલન"
  },
  {
    "serial_number": 975,
    "word": "નવ"
  },
  {
    "serial_number": 976,
    "word": "ટ્રક"
  },
  {
    "serial_number": 977,
    "word": "અવાજ"
  },
  {
    "serial_number": 978,
    "word": "સ્તર"
  },
  {
    "serial_number": 979,
    "word": "તક"
  },
  {
    "serial_number": 980,
    "word": "ભેગા"
  },
  {
    "serial_number": 981,
    "word": "દુકાન"
  },
  {
    "serial_number": 982,
    "word": "ઉંચાઇ"
  },
  {
    "serial_number": 983,
    "word": "ફેંકવું"
  },
  {
    "serial_number": 984,
    "word": "ચમકવા"
  },
  {
    "serial_number": 985,
    "word": "મિલકત"
  },
  {
    "serial_number": 986,
    "word": "કૉલમ"
  },
  {
    "serial_number": 987,
    "word": "પરમાણુ"
  },
  {
    "serial_number": 988,
    "word": "પસંદ"
  },
  {
    "serial_number": 989,
    "word": "ખોટું"
  },
  {
    "serial_number": 990,
    "word": "ગ્રે"
  },
  {
    "serial_number": 991,
    "word": "વારંવાર"
  },
  {
    "serial_number": 992,
    "word": "જરૂરી"
  },
  {
    "serial_number": 993,
    "word": "વ્યાપક"
  },
  {
    "serial_number": 994,
    "word": "તૈયાર"
  },
  {
    "serial_number": 995,
    "word": "મીઠું"
  },
  {
    "serial_number": 996,
    "word": "નાક"
  },
  {
    "serial_number": 997,
    "word": "બહુવચન"
  },
  {
    "serial_number": 998,
    "word": "ગુસ્સો"
  },
  {
    "serial_number": 999,
    "word": "દાવો"
  },
  {
    "serial_number": 1000,
    "word": "ખંડ"
  }
]